prelogging/__init__.py
prelogging/_version.py
prelogging/formatter_presets.py
prelogging/formatter_presets.txt
prelogging/lcdict.py
prelogging/lcdict_builder_abc.py
prelogging/lcdictbasic.py
prelogging/locking_handlers.py
prelogging/six.py
prelogging-0.4.3.dist-info/METADATA
prelogging-0.4.3.dist-info/RECORD
prelogging-0.4.3.dist-info/WHEEL
prelogging-0.4.3.dist-info/top_level.txt
